TOPSIS_MAIN/__init__.py
TOPSIS_MAIN/topsis.py
topsis_purnika_102303412-1.0.2.dist-info/METADATA
topsis_purnika_102303412-1.0.2.dist-info/WHEEL
topsis_purnika_102303412-1.0.2.dist-info/entry_points.txt
topsis_purnika_102303412-1.0.2.dist-info/top_level.txt
topsis_purnika_102303412-1.0.2.dist-info/RECORD
