Metadata-Version: 2.4
Name: topsis-purnika-102303412
Version: 1.0.2
Summary: This package implements the TOPSIS method for multi-criteria decision making using a command-line interface. It allows users to rank alternatives from a CSV file by specifying custom weights and impacts. The package includes input validation and generates a ranked output file efficiently. It is designed for academic and practical decision-analysis use.
Author: Purnika Malhotra
Author-email: purnikamalhotra53@gmail.com
Requires-Python: >=3.8
Requires-Dist: pandas
Requires-Dist: numpy
Dynamic: author
Dynamic: author-email
Dynamic: description
Dynamic: description-content-type
Dynamic: requires-dist
Dynamic: requires-python
Dynamic: summary
